NiChart_DLMUSE/CalcROIVol.py
NiChart_DLMUSE/MaskImage.py
NiChart_DLMUSE/RelabelROI.py
NiChart_DLMUSE/ReorientImage.py
NiChart_DLMUSE/SegmentImage.py
NiChart_DLMUSE/__init__.py
NiChart_DLMUSE/__main__.py
NiChart_DLMUSE/dlmuse_pipeline.py
NiChart_DLMUSE/utils.py
NiChart_DLMUSE/shared/dicts/MUSE_ROI_complete_list.csv
NiChart_DLMUSE/shared/dicts/MUSE_ROI_complete_list.json
NiChart_DLMUSE/shared/dicts/MUSE_mapping_consecutive_indices.csv
NiChart_DLMUSE/shared/dicts/MUSE_mapping_derived_rois.csv
tests/__init__.py
tests/test_utils.py
NiChart_DLMUSE-1.0.9.dist-info/LICENSE
NiChart_DLMUSE-1.0.9.dist-info/METADATA
NiChart_DLMUSE-1.0.9.dist-info/WHEEL
NiChart_DLMUSE-1.0.9.dist-info/entry_points.txt
NiChart_DLMUSE-1.0.9.dist-info/top_level.txt
NiChart_DLMUSE-1.0.9.dist-info/RECORD
