Metadata-Version: 2.1
Name: NiChart_DLMUSE
Version: 1.0.9
Summary: Run NiChart_DLMUSE on your data (currently only structural pipeline is supported).
Home-page: https://github.com/CBICA/NiChart_DLMUSE
Author: Guray Erus, Wu Di, Kyunglok Baik, George Aidinis
Author-email: software@cbica.upenn.edu
Maintainer: Guray Erus, Kyunglok Baik, Spiros Maggioros, Alexander Getka
License: By installing/using DLMUSE, the user agrees to the following license: See https://www.med.upenn.edu/cbica/software-agreement-non-commercial.html
Keywords: deep learning,image segmentation,semantic segmentation,medical image analysis,medical image segmentation,nnU-Net,nnunet
Classifier: Intended Audience :: Science/Research
Classifier: Programming Language :: Python
Classifier: Topic :: Scientific/Engineering
Classifier: Operating System :: Unix
Requires-Python: >=3.9
License-File: LICENSE
Requires-Dist: torch<=2.2.1
Requires-Dist: DLICV
Requires-Dist: DLMUSE
Requires-Dist: huggingface_hub
Requires-Dist: scipy
Requires-Dist: nibabel
Requires-Dist: argparse
Requires-Dist: pathlib
